aiida_inq/__init__.py
aiida_inq/calculations/__init__.py
aiida_inq/calculations/inq.py
aiida_inq/calculations/functions/create_kpoints_from_distance.py
aiida_inq/parsers/__init__.py
aiida_inq/parsers/inq.py
aiida_inq/workflows/__init__.py
aiida_inq/workflows/base.py
aiida_inq/workflows/convergence.py
aiida_inq/workflows/tddft.py
aiida_inq/workflows/protocols/__init__.py
aiida_inq/workflows/protocols/utils.py
aiida_inq/workflows/protocols/inq/base.yaml
aiida_inq/workflows/protocols/inq/convergence.yaml
aiida_inq/workflows/protocols/inq/tddft.yaml
aiida_inq/workflows/protocols/pseudos/pseudos.yaml
aiida_inq-0.1.0.dist-info/entry_points.txt
aiida_inq-0.1.0.dist-info/LICENSE.txt
aiida_inq-0.1.0.dist-info/WHEEL
aiida_inq-0.1.0.dist-info/METADATA
aiida_inq-0.1.0.dist-info/RECORD
